README.txt
setup.cfg
setup.py
Products/__init__.py
Products.Plone2FSS.egg-info/PKG-INFO
Products.Plone2FSS.egg-info/SOURCES.txt
Products.Plone2FSS.egg-info/dependency_links.txt
Products.Plone2FSS.egg-info/entry_points.txt
Products.Plone2FSS.egg-info/namespace_packages.txt
Products.Plone2FSS.egg-info/not-zip-safe
Products.Plone2FSS.egg-info/paster_plugins.txt
Products.Plone2FSS.egg-info/requires.txt
Products.Plone2FSS.egg-info/top_level.txt
Products/Plone2FSS/__init__.py
Products/Plone2FSS/configure.zcml
Products/Plone2FSS/tests.py
Products/Plone2FSS/browser/__init__.py
Products/Plone2FSS/browser/configure.zcml
Products/Plone2FSS/browser/plone2fss.pt
Products/Plone2FSS/browser/plone2fss.py
docs/HISTORY.txt
docs/INSTALL.txt
docs/LICENSE.GPL
docs/LICENSE.txt