Metadata-Version: 1.0
Name: Products.Plone2FSS
Version: 0.4.0beta
Summary: Export File and Image fields from Plone content type to a FSS valid format
Home-page: http://plone.org/products/products.plone2fss
Author: Keul (Luca Fabbri)
Author-email: luca.fabbri@redturtle.net
License: GPL
Keywords: iw fss plone file image migration
Platform: UNKNOWN
Classifier: Framework :: Plone
Classifier: Programming Language :: Python
Classifier: Topic :: Software Development :: Libraries :: Python Modules
